tamida/__init__.py
tamida/analysis_square.py
tamida-0.1.1.dist-info/METADATA
tamida-0.1.1.dist-info/WHEEL
tamida-0.1.1.dist-info/top_level.txt
tamida-0.1.1.dist-info/RECORD
