Metadata-Version: 2.2
Name: tamida
Version: 0.1.1
Summary: Một thư viện toán học hỗ trợ số chính phương, số nguyên tố, giai thừa, ...
Home-page: https://github.com/dangminhtai/
Author: Đặng Minh Tài
Author-email: dmt826321@gmail.com
Classifier: Programming Language :: Python :: 3
Classifier: License :: OSI Approved :: MIT License
Classifier: Operating System :: OS Independent
Requires-Python: >=3.6
Requires-Dist: scipy
Dynamic: author
Dynamic: author-email
Dynamic: classifier
Dynamic: description
Dynamic: description-content-type
Dynamic: home-page
Dynamic: requires-dist
Dynamic: requires-python
Dynamic: summary
